{"pageProps":{"id":2,"title":"Car Yard Soaping Service","titleTwo":"Car Yard Soaping Service","shortDesc":"Perfect for sales or if your yard has been left neglected for a while!.. ","description":"<p>Perfect for sales or if your yard has been left neglected for a while!</P><p>A team of highly trained detailers will:</p> <ol><li>- Thoroughly house each vehicle</li><li> Will soap the vehicle using a high end soaping/wax compound (perfect for removing pollen anddirt)</li><li>Will hose the vehicle again to remove soaping suds</li><li>Finish off with a Chamois service</li></ol><p>This service can be organised into your yards cleaning protocol in a weekly, fortnightly, monthly oron a request basis.</p><p>This will make your yard look brand new!</p>","descriptionTwo":"<p>Perfect for sales or if your yard has been left neglected for a while!</P><p>A team of highly trained detailers will:</p> <ol><li>- Thoroughly house each vehicle</li><li> Will soap the vehicle using a high end soaping/wax compound (perfect for removing pollen anddirt)</li><li>Will hose the vehicle again to remove soaping suds</li><li>Finish off with a Chamois service</li></ol><p>This service can be organised into your yards cleaning protocol in a weekly, fortnightly, monthly oron a request basis.</p><p>This will make your yard look brand new!</p>","thumb":"img36.png","icon":"icon-glyph-252","singleThumb":"img36.png"},"__N_SSG":true}